<Source file="./0000950123-10-102136.nc">
<SUBMISSION ACCESSION-NUMBER="0000950123-10-102136" DATE-OF-FILING-DATE-CHANGE="20101108" FILING-DATE="20101108" PUBLIC-DOCUMENT-COUNT="36" TYPE="FWP"><SUBJECT-COMPANY><COMPANY-DATA ASSIGNED-SIC="6022" CIK="0000039311" CONFORMED-NAME="INDEPENDENT BANK CORP /MI/" FISCAL-YEAR-END="1231" IRS-NUMBER="382032782" STATE-OF-INCORPORATION="MI" /><FILING-VALUES ACT="34" FILE-NUMBER="333-168032" FILM-NUMBER="101170713" FORM-TYPE="FWP" /><BUSINESS-ADDRESS CITY="IONIA" PHONE="6165279450" STATE="MI" STREET1="230 W MAIN ST" STREET2="PO BOX 491" ZIP="48846" /><MAIL-ADDRESS CITY="IONIA" STATE="MI" STREET1="230 W MAIN ST" ZIP="48846" /></SUBJECT-COMPANY><FILED-BY><COMPANY-DATA ASSIGNED-SIC="6022" CIK="0000039311" CONFORMED-NAME="INDEPENDENT BANK CORP /MI/" FISCAL-YEAR-END="1231" IRS-NUMBER="382032782" STATE-OF-INCORPORATION="MI" /><FILING-VALUES FORM-TYPE="FWP" /><BUSINESS-ADDRESS CITY="IONIA" PHONE="6165279450" STATE="MI" STREET1="230 W MAIN ST" STREET2="PO BOX 491" ZIP="48846" /><MAIL-ADDRESS CITY="IONIA" STATE="MI" STREET1="230 W MAIN ST" ZIP="48846" /></FILED-BY></SUBMISSION></Source>
