<Source file="./0000739708-10-000016.nc">
<SUBMISSION ACCESSION-NUMBER="0000739708-10-000016" DATE-OF-FILING-DATE-CHANGE="20101108" FILING-DATE="20101108" PERIOD="20101108" PUBLIC-DOCUMENT-COUNT="2" TYPE="8-K"><FILER><COMPANY-DATA ASSIGNED-SIC="4832" CIK="0001400891" CONFORMED-NAME="CC Media Holdings Inc" FISCAL-YEAR-END="1231" IRS-NUMBER="260241222" /><FILING-VALUES ACT="34" FILE-NUMBER="000-53354" FILM-NUMBER="101172451" FORM-TYPE="8-K" /><BUSINESS-ADDRESS CITY="SAN ANTONIO" PHONE="210-832-3314" STATE="TX" STREET1="200 EAST BASSE ROAD" ZIP="78209" /><MAIL-ADDRESS CITY="SAN ANTONIO" STATE="TX" STREET1="200 EAST BASSE ROAD" ZIP="78209" /><FORMER-COMPANY DATE-CHANGED="20070730" FORMER-CONFORMED-NAME="C C Media Holdings Inc" /><FORMER-COMPANY DATE-CHANGED="20070524" FORMER-CONFORMED-NAME="BT Triple Crown Capital Holdings III, Inc." /></FILER></SUBMISSION></Source>
