<Source file="./0000950123-10-102474.nc">
<SUBMISSION ACCESSION-NUMBER="0000950123-10-102474" DATE-OF-FILING-DATE-CHANGE="20101108" FILING-DATE="20101108" PERIOD="20100930" PUBLIC-DOCUMENT-COUNT="5" TYPE="10-Q"><FILER><COMPANY-DATA ASSIGNED-SIC="6798" CIK="0001254595" CONFORMED-NAME="FIRST POTOMAC REALTY TRUST" FISCAL-YEAR-END="1231" IRS-NUMBER="371470730" STATE-OF-INCORPORATION="MD" /><FILING-VALUES ACT="34" FILE-NUMBER="001-31824" FILM-NUMBER="101172655" FORM-TYPE="10-Q" /><BUSINESS-ADDRESS CITY="BETHESDA" PHONE="3019869200" STATE="MD" STREET1="7600 WISCONSIN AVENUE" STREET2="11TH FLOOR" ZIP="20814" /><MAIL-ADDRESS CITY="BETHESDA" STATE="MD" STREET1="7600 WISCONSIN AVENUE" STREET2="11TH FLOOR" ZIP="20814" /></FILER></SUBMISSION></Source>
