<Source file="./0000898531-10-000754.nc">
<SUBMISSION ACCESSION-NUMBER="0000898531-10-000754" DATE-OF-FILING-DATE-CHANGE="20101108" EFFECTIVENESS-DATE="20101108" FILING-DATE="20101108" PERIOD="20100831" PUBLIC-DOCUMENT-COUNT="6" TYPE="N-CSRS"><FILER><COMPANY-DATA CIK="0001027596" CONFORMED-NAME="ADVISORS SERIES TRUST" FISCAL-YEAR-END="1031" IRS-NUMBER="000000000" STATE-OF-INCORPORATION="DE" /><FILING-VALUES ACT="40" FILE-NUMBER="811-07959" FILM-NUMBER="101171261" FORM-TYPE="N-CSRS" /><BUSINESS-ADDRESS CITY="MILWAUKEE" PHONE="414-765-5340" STATE="WI" STREET1="U.S BANCORP FUND SERVICES, LLC" STREET2="615 E MICHIGAN STREET" ZIP="53202" /><MAIL-ADDRESS CITY="MILWAUKEE" STATE="WI" STREET1="615 E MICHIGAN STREET" STREET2="MK-WI-LC2" ZIP="53202" /></FILER><SERIES-AND-CLASSES-CONTRACTS-DATA><EXISTING-SERIES-AND-CLASSES-CONTRACTS><SERIES OWNER-CIK="0001027596" SERIES-ID="S000000021" SERIES-NAME="American Trust Allegiance Fund"><CLASS-CONTRACT CLASS-CONTRACT-ID="C000000034" CLASS-CONTRACT-NAME="Investor Class" CLASS-CONTRACT-TICKER-SYMBOL="ATAFX" /></SERIES></EXISTING-SERIES-AND-CLASSES-CONTRACTS></SERIES-AND-CLASSES-CONTRACTS-DATA></SUBMISSION></Source>
