<Source file="./0001193125-10-251493.nc">
<SUBMISSION ACCESSION-NUMBER="0001193125-10-251493" DATE-OF-FILING-DATE-CHANGE="20101108" FILING-DATE="20101108" PERIOD="20100929" PUBLIC-DOCUMENT-COUNT="10" TYPE="10-Q"><FILER><COMPANY-DATA ASSIGNED-SIC="5812" CIK="0000703351" CONFORMED-NAME="BRINKER INTERNATIONAL INC" FISCAL-YEAR-END="0625" IRS-NUMBER="751914582" STATE-OF-INCORPORATION="DE" /><FILING-VALUES ACT="34" FILE-NUMBER="001-10275" FILM-NUMBER="101171226" FORM-TYPE="10-Q" /><BUSINESS-ADDRESS CITY="DALLAS" PHONE="9729809917" STATE="TX" STREET1="6820 LBJ FREEWAY" ZIP="75240" /><MAIL-ADDRESS CITY="DALLAS" STATE="TX" STREET1="6820 LBJ FREEWAY" ZIP="75240" /><FORMER-COMPANY DATE-CHANGED="19910528" FORMER-CONFORMED-NAME="CHILIS INC" /></FILER></SUBMISSION></Source>
