<Source file="./0001137050-10-000226.nc">
<SUBMISSION ACCESSION-NUMBER="0001137050-10-000226" DATE-OF-FILING-DATE-CHANGE="20101108" FILING-DATE="20101108" PERIOD="20100930" PUBLIC-DOCUMENT-COUNT="5" TYPE="10-Q"><FILER><COMPANY-DATA ASSIGNED-SIC="6351" CIK="0001116204" CONFORMED-NAME="SINO ASSURANCE INC." FISCAL-YEAR-END="1231" IRS-NUMBER="522175896" STATE-OF-INCORPORATION="DE" /><FILING-VALUES ACT="34" FILE-NUMBER="000-50002" FILM-NUMBER="101171431" FORM-TYPE="10-Q" /><BUSINESS-ADDRESS CITY="SHENZHEN" PHONE="86-0755-82520166" STATE="F4" STREET1="17TH FLOOR 6009 YITIAN ROAD" STREET2="NEW WORLD CENTRE, FUTIAN DISTRICT" ZIP="518000" /><MAIL-ADDRESS CITY="SHENZHEN" STATE="F4" STREET1="17TH FLOOR 6009 YITIAN ROAD" STREET2="NEW WORLD CENTRE, FUTIAN DISTRICT" ZIP="518000" /><FORMER-COMPANY DATE-CHANGED="20041206" FORMER-CONFORMED-NAME="DIGITAL NETWORK ALLIANCE INTERNATIONAL, INC." /><FORMER-COMPANY DATE-CHANGED="20000606" FORMER-CONFORMED-NAME="SHEFFIELD PRODUCTS INC / DE" /></FILER></SUBMISSION></Source>
