<Source file="./0001193125-10-252170.nc">
<SUBMISSION ACCESSION-NUMBER="0001193125-10-252170" DATE-OF-FILING-DATE-CHANGE="20101108" FILING-DATE="20101108" PERIOD="20101108" PUBLIC-DOCUMENT-COUNT="33" TYPE="8-K"><FILER><COMPANY-DATA ASSIGNED-SIC="4813" CIK="0001328571" CONFORMED-NAME="NTELOS HOLDINGS CORP" IRS-NUMBER="364573125" /><FILING-VALUES ACT="34" FILE-NUMBER="000-51798" FILM-NUMBER="101172811" FORM-TYPE="8-K" /><BUSINESS-ADDRESS CITY="WAYNESBORO" PHONE="5409463500" STATE="VA" STREET1="401 SPRING LANE, SUITE 300" STREET2="P.O. BOX 1990" ZIP="22980" /><MAIL-ADDRESS CITY="WAYNESBORO" STATE="VA" STREET1="401 SPRING LANE, SUITE 300" STREET2="P.O. BOX 1990" ZIP="22980" /></FILER></SUBMISSION></Source>
