<Source file="./0001313345-10-000008.nc">
<SUBMISSION ACCESSION-NUMBER="0001313345-10-000008" DATE-OF-FILING-DATE-CHANGE="20101108" EFFECTIVENESS-DATE="20101108" FILING-DATE="20101108" PERIOD="20100930" PUBLIC-DOCUMENT-COUNT="1" TYPE="13F-HR"><FILER><COMPANY-DATA CIK="0001313345" CONFORMED-NAME="TIEDEMANN TRUST CO" IRS-NUMBER="000000000" /><FILING-VALUES ACT="34" FILE-NUMBER="028-12765" FILM-NUMBER="101171410" FORM-TYPE="13F-HR" /><BUSINESS-ADDRESS CITY="WILMINGTON" PHONE="302-656-5644" STATE="DE" STREET1="1201 NORTH MARKET STREET" STREET2="SUITE 1406" ZIP="19801" /><MAIL-ADDRESS CITY="WILMINGTON" STATE="DE" STREET1="1201 NORTH MARKET STREET" STREET2="SUITE 1406" ZIP="19801" /></FILER></SUBMISSION></Source>
