<Source file="./0001269373-10-000003.nc">
<SUBMISSION ACCESSION-NUMBER="0001269373-10-000003" DATE-OF-FILING-DATE-CHANGE="20101108" FILING-DATE="20101108" PERIOD="20101104" PUBLIC-DOCUMENT-COUNT="1" TYPE="4"><REPORTING-OWNER><OWNER-DATA CIK="0001269373" CONFORMED-NAME="HEAD STEPHEN R" /><FILING-VALUES ACT="34" FILE-NUMBER="000-27385" FILM-NUMBER="101172385" FORM-TYPE="4" /></REPORTING-OWNER><ISSUER><COMPANY-DATA ASSIGNED-SIC="7372" CIK="0001083318" CONFORMED-NAME="INTERACTIVE INTELLIGENCE INC" FISCAL-YEAR-END="1231" IRS-NUMBER="351933097" STATE-OF-INCORPORATION="IN" /><BUSINESS-ADDRESS CITY="INDIANAPOLIS" PHONE="3178723000" STATE="IN" STREET1="7601 INTERACTIVE WAY" ZIP="46278" /><MAIL-ADDRESS CITY="INDIANAPOLIS" STATE="IN" STREET1="7601 INTERACTIVE WAY" ZIP="46278" /></ISSUER></SUBMISSION><ownershipDocument documentType="4" periodOfReport="2010-11-04" schemaVersion="X0303">
<issuer> issuerCik="0001083318" 
 issuerName="INTERACTIVE INTELLIGENCE INC" 
 issuerTradingSymbol="ININ" 
</issuer>
<reportingOwner>
<reportingOwnerId> rptOwnerCik="0001269373" 
 rptOwnerName="HEAD STEPHEN R" 
</reportingOwnerId>
<reportingOwnerAddress rptOwnerCity="INDIANAPOLIS" rptOwnerState="IN" rptOwnerStreet1="7601 INTERACTIVE WAY" rptOwnerStreet2="" rptOwnerZipCode="46278" />


<reportingOwnerRelationship isDirector="0" isOfficer="1" isOther="0" isTenPercentOwner="0" officerTitle="Chief Financial Officer">
</reportingOwnerRelationship>
</reportingOwner>
<nonDerivativeTable><nonDerivativeTransaction><securityTitle> value="Common Stock" 
</securityTitle>
<transactionDate value="2010-11-04">
</transactionDate>
<transactionCoding equitySwapInvolved="0" transactionCode="M" transactionFormType="4">
</transactionCoding>
<transactionAmounts>
<transactionShares> value="6250" 
</transactionShares>
<transactionPricePerShare value="4.20">
</transactionPricePerShare>
<transactionAcquiredDisposedCode value="A">
</transactionAcquiredDisposedCode>
</transactionAmounts>
<postTransactionAmounts><sharesOwnedFollowingTransaction> value="36200" 
</sharesOwnedFollowingTransaction>
</postTransactionAmounts>
<ownershipNature><directOrIndirectOwnership> value="D" 
</directOrIndirectOwnership>
<natureOfOwnership>
<value /> 
</natureOfOwnership>
</ownershipNature>
</nonDerivativeTransaction>
<nonDerivativeTransaction><securityTitle> value="Common Stock" 
</securityTitle>
<transactionDate value="2010-11-04">
</transactionDate>
<transactionCoding equitySwapInvolved="0" transactionCode="S" transactionFormType="4">
</transactionCoding>
<transactionAmounts>
<transactionShares> value="6250" 
</transactionShares>
<transactionPricePerShare value="26.76">
<footnoteId id="F1" /> 
</transactionPricePerShare>
<transactionAcquiredDisposedCode> value="D" 
</transactionAcquiredDisposedCode>
</transactionAmounts>
<postTransactionAmounts><sharesOwnedFollowingTransaction> value="29950" 
</sharesOwnedFollowingTransaction>
</postTransactionAmounts>
<ownershipNature><directOrIndirectOwnership> value="D" 
</directOrIndirectOwnership>
<natureOfOwnership>
<value /> 
</natureOfOwnership>
</ownershipNature>
</nonDerivativeTransaction>
<nonDerivativeTransaction><securityTitle> value="Common Stock" 
</securityTitle>
<transactionDate value="2010-11-05">
</transactionDate>
<transactionCoding equitySwapInvolved="0" transactionCode="M" transactionFormType="4">
</transactionCoding>
<transactionAmounts>
<transactionShares> value="3750" 
</transactionShares>
<transactionPricePerShare value="5.17">
</transactionPricePerShare>
<transactionAcquiredDisposedCode value="A">
</transactionAcquiredDisposedCode>
</transactionAmounts>
<postTransactionAmounts><sharesOwnedFollowingTransaction> value="33700" 
</sharesOwnedFollowingTransaction>
</postTransactionAmounts>
<ownershipNature><directOrIndirectOwnership> value="D" 
</directOrIndirectOwnership>
<natureOfOwnership>
<value /> 
</natureOfOwnership>
</ownershipNature>
</nonDerivativeTransaction>
<nonDerivativeTransaction><securityTitle> value="Common Stock" 
</securityTitle>
<transactionDate value="2010-11-05">
</transactionDate>
<transactionCoding equitySwapInvolved="0" transactionCode="S" transactionFormType="4">
</transactionCoding>
<transactionAmounts>
<transactionShares> value="3750" 
</transactionShares>
<transactionPricePerShare value="27.42">
<footnoteId id="F2" /> 
</transactionPricePerShare>
<transactionAcquiredDisposedCode> value="D" 
</transactionAcquiredDisposedCode>
</transactionAmounts>
<postTransactionAmounts><sharesOwnedFollowingTransaction> value="29950" 
</sharesOwnedFollowingTransaction>
</postTransactionAmounts>
<ownershipNature><directOrIndirectOwnership> value="D" 
</directOrIndirectOwnership>
<natureOfOwnership>
<value /> 
</natureOfOwnership>
</ownershipNature>
</nonDerivativeTransaction>
<nonDerivativeHolding><securityTitle> value="Common Stock" 
</securityTitle>
<postTransactionAmounts>
<sharesOwnedFollowingTransaction> value="550" 
</sharesOwnedFollowingTransaction>
</postTransactionAmounts>
<ownershipNature><directOrIndirectOwnership> value="I" 
</directOrIndirectOwnership>
<natureOfOwnership value="By Daughter">
</natureOfOwnership>
</ownershipNature>
</nonDerivativeHolding>
</nonDerivativeTable>
<derivativeTable><derivativeTransaction><securityTitle> value="Stock Option (right to buy)" 
</securityTitle>
<conversionOrExercisePrice value="4.20">
</conversionOrExercisePrice>
<transactionDate value="2010-11-04">
</transactionDate>
<transactionCoding equitySwapInvolved="0" transactionCode="M" transactionFormType="4">
</transactionCoding>
<transactionAmounts>
<transactionShares> value="6250" 
</transactionShares>
<transactionPricePerShare value="0">
</transactionPricePerShare>
<transactionAcquiredDisposedCode value="D">
</transactionAcquiredDisposedCode>
</transactionAmounts>
<exerciseDate><footnoteId id="F3" /> 
</exerciseDate>
<expirationDate> value="2011-02-17" 
</expirationDate>
<underlyingSecurity>
<underlyingSecurityTitle> value="Common Stock" 
</underlyingSecurityTitle>
<underlyingSecurityShares value="6250">
</underlyingSecurityShares>
</underlyingSecurity>
<postTransactionAmounts><sharesOwnedFollowingTransaction> value="0" 
</sharesOwnedFollowingTransaction>
</postTransactionAmounts>
<ownershipNature><directOrIndirectOwnership> value="D" 
</directOrIndirectOwnership>
<natureOfOwnership>
<value /> 
</natureOfOwnership>
</ownershipNature>
</derivativeTransaction>
<derivativeTransaction><securityTitle> value="Stock Option (right to buy)" 
</securityTitle>
<conversionOrExercisePrice value="5.17">
</conversionOrExercisePrice>
<transactionDate value="2010-11-05">
</transactionDate>
<transactionCoding equitySwapInvolved="0" transactionCode="M" transactionFormType="4">
</transactionCoding>
<transactionAmounts>
<transactionShares> value="3750" 
</transactionShares>
<transactionPricePerShare value="0">
</transactionPricePerShare>
<transactionAcquiredDisposedCode value="D">
</transactionAcquiredDisposedCode>
</transactionAmounts>
<exerciseDate><footnoteId id="F4" /> 
</exerciseDate>
<expirationDate> value="2012-01-27" 
</expirationDate>
<underlyingSecurity>
<underlyingSecurityTitle> value="Common Stock" 
</underlyingSecurityTitle>
<underlyingSecurityShares value="3750">
</underlyingSecurityShares>
</underlyingSecurity>
<postTransactionAmounts><sharesOwnedFollowingTransaction> value="1250" 
</sharesOwnedFollowingTransaction>
</postTransactionAmounts>
<ownershipNature><directOrIndirectOwnership> value="D" 
</directOrIndirectOwnership>
<natureOfOwnership>
<value /> 
</natureOfOwnership>
</ownershipNature>
</derivativeTransaction>
</derivativeTable>
<footnotes>
<footnote id="F1" text="Represents the sale of 6,250 shares in nine separate transactions, ranging in price from $26.55 to $27.32 per share, resulting in a weighted average sale price per share of $26.764413. The reporting person will provide upon request by the SEC staff, the Issuer or a security holder of the Issuer, full information regarding the number of shares sold at each separate price within the range." /> 
 <footnote id="F2" text="Represents the sale of 3,750 shares in six separate transactions, ranging in price from $27.37 to $27.50 per share, resulting in a weighted average sale price per share of $27.421550. The reporting person will provide upon request by the SEC staff, the Issuer or a security holder of the Issuer, full information regarding the number of shares sold at each separate price within the range." /> 
 <footnote id="F3" text="1,563 shares vested on each of 2/17/2006 and 2/17/2007 and 1,562 shares vested on each of 2/17/2008 and 2/17/2009." /> 
 <footnote id="F4" text="5,000 shares vested on 1/27/2007." /> 
</footnotes>
<remarks />
<ownerSignature> signatureName="Ashley Vukovits, Attorney-in-fact" 
 signatureDate="2010-11-08" 
</ownerSignature>
</ownershipDocument></Source>
